snow/__init__.py
snow/app.py
snow/config.py
snow/consts.py
snow/exceptions.py
snow/model/__init__.py
snow/model/base.py
snow/model/schema/__init__.py
snow/model/schema/base.py
snow/model/schema/fields/__init__.py
snow/model/schema/fields/base.py
snow/model/schema/fields/boolean.py
snow/model/schema/fields/choice.py
snow/model/schema/fields/datetime.py
snow/model/schema/fields/email.py
snow/model/schema/fields/integer.py
snow/model/schema/fields/mapped.py
snow/model/schema/fields/string.py
snow/model/schema/fields/utils.py
snow/model/schema/helpers/__init__.py
snow/model/schema/helpers/pluck.py
snow/model/schema/partial.py
snow/models/__init__.py
snow/models/table/__init__.py
snow/models/table/schema.py
snow/query/__init__.py
snow/query/builder.py
snow/query/condition.py
snow/query/operators.py
snow/query/utils.py
snow/request/__init__.py
snow/request/base.py
snow/request/delete.py
snow/request/get.py
snow/request/helpers/__init__.py
snow/request/helpers/pagestream.py
snow/request/methods.py
snow/request/patch.py
snow/request/post.py
snow/request/response/__init__.py
snow/request/response/schemas.py
snow/schemas/__init__.py
snow/schemas/table/__init__.py
snow/schemas/table/incident.py
snow/session.py
snow/utils.py
snow-0.3.0.dist-info/LICENSE
snow-0.3.0.dist-info/WHEEL
snow-0.3.0.dist-info/METADATA
snow-0.3.0.dist-info/RECORD
