Metadata-Version: 2.1
Name: snow
Version: 0.3.0
Summary: Python asyncio library for ServiceNow
Home-page: https://github.com/rbw/snow
License: MIT
Author: Robert Wikman
Author-email: rbw@vault13.org
Requires-Python: >=3.7,<4.0
Classifier: Development Status :: 3 - Alpha
Classifier: License :: OSI Approved :: MIT License
Classifier: Operating System :: OS Independent
Classifier: Programming Language :: Python :: 3
Classifier: Programming Language :: Python :: 3.7
Classifier: Programming Language :: Python :: 3.8
Classifier: Topic :: Software Development :: Libraries
Requires-Dist: aiohttp (>=3.6.2,<4.0.0)
Requires-Dist: marshmallow (>=3.6.1,<4.0.0)
